stackit/serviceenablement/__init__.py
stackit/serviceenablement/api/__init__.py
stackit/serviceenablement/api/default_api.py
stackit/serviceenablement/api_client.py
stackit/serviceenablement/api_response.py
stackit/serviceenablement/configuration.py
stackit/serviceenablement/exceptions.py
stackit/serviceenablement/models/__init__.py
stackit/serviceenablement/models/action_error.py
stackit/serviceenablement/models/check_service.py
stackit/serviceenablement/models/cloud_service.py
stackit/serviceenablement/models/dependencies.py
stackit/serviceenablement/models/error_response.py
stackit/serviceenablement/models/list_service_status_regional200_response.py
stackit/serviceenablement/models/parameters.py
stackit/serviceenablement/models/parameters_general.py
stackit/serviceenablement/models/service_status.py
stackit/serviceenablement/py.typed
stackit/serviceenablement/rest.py
stackit_serviceenablement-1.1.1.dist-info/METADATA
stackit_serviceenablement-1.1.1.dist-info/WHEEL
stackit_serviceenablement-1.1.1.dist-info/licenses/LICENSE.md
stackit_serviceenablement-1.1.1.dist-info/licenses/NOTICE.txt
stackit_serviceenablement-1.1.1.dist-info/RECORD
